odk_mailer/__init__.py
odk_mailer/before.py
odk_mailer/classes/Config.py
odk_mailer/classes/Fields.py
odk_mailer/classes/JobMeta.py
odk_mailer/classes/Mailer.py
odk_mailer/classes/Mailjob.py
odk_mailer/classes/Message.py
odk_mailer/classes/Schedule.py
odk_mailer/classes/Source.py
odk_mailer/classes/__init__.py
odk_mailer/classes/odk_api.py
odk_mailer/commands.py
odk_mailer/lib/__init__.py
odk_mailer/lib/cron.py
odk_mailer/lib/db.py
odk_mailer/lib/globals.py
odk_mailer/lib/log.py
odk_mailer/lib/notification.py
odk_mailer/lib/parser.py
odk_mailer/lib/prompts.py
odk_mailer/lib/smtp.py
odk_mailer/lib/utils.py
odk_mailer/lib/validators.py
odk_mailer/main.py
odk_mailer-0.7.3.dist-info/METADATA
odk_mailer-0.7.3.dist-info/WHEEL
odk_mailer-0.7.3.dist-info/entry_points.txt
odk_mailer-0.7.3.dist-info/RECORD
