Metadata-Version: 2.1
Name: odk-mailer
Version: 0.7.3
Summary: A simple CLI for sending form related mails in the context of Open Data Kit (ODK) 
Author: tertek
Author-email: ekin.tertemiz@swisstph.ch
Requires-Python: >=3.10,<4.0
Classifier: Programming Language :: Python :: 3
Classifier: Programming Language :: Python :: 3.10
Classifier: Programming Language :: Python :: 3.11
Classifier: Programming Language :: Python :: 3.12
Requires-Dist: email-validator (>=2.1.0.post1,<3.0.0)
Requires-Dist: inquirer (>=3.1.4,<4.0.0)
Requires-Dist: python-crontab (>=3.0.0,<4.0.0)
Requires-Dist: python-dotenv (>=1.0.0,<2.0.0)
Requires-Dist: requests (>=2.31.0,<3.0.0)
Requires-Dist: toml (>=0.10.2,<0.11.0)
Requires-Dist: typer[all] (>=0.9.0,<0.10.0)
